{
  "name": "Форма",
  "sections": [
    {
      "legend": "Общие",
      "name": "type",
      "fields": [
        {
          "type": "string",
          "label": "Адрес поиск по справочнику"
        },
        {
          "type": "string",
          "label": "Юридический адрес"
        },
        {
          "type": "switch",
          "label": "Скрыть точный адрес в объявлении"
        },
        {
          "type": "string",
          "label": "Название ЖК"
        },
        {
          "type": "number",
          "label": "Корпус"
        },
        {
          "type": "string",
          "label": "Кадастровый номер"
        },
        {
          "type": "string",
          "label": "Номер налоговой"
        },
        {
          "type": "select",
          "label": "Тип помещения",
          "options": ["1", "2", "3"]
        },
        {
          "type": "number",
          "label": "Общая площадь",
          "units": "м2"
        },
        {
          "type": "switch",
          "label": "Возможна аренда/продажа частями"
        },
        {
          "type": "number",
          "label": "Этаж"
        },
        {
          "type": "number",
          "label": "Этажность"
        },
        {
          "type": "number",
          "label": "Высота потолков",
          "units": "м"
        },
        {
          "type": "switch",
          "label": "Витринные окна"
        },
        {
          "type": "switch",
          "label": "Помещение занято"
        },
        {
          "type": "string",
          "label": "Планировка"
        },
        {
          "type": "string",
          "label": "Сетка колон"
        },
        {
          "type": "string",
          "label": "Материал пола"
        }
      ]
    },
    {
      "legend": "Коммуникации",
      "name": "communications",
      "fields": [
        {
          "name": "Лифты (для зданий)",
          "type": "string",
          "min": 0,
          "step": 1
        },
        {
          "name": "Лифты (для складов)",
          "type": "string",
          "min": 0,
          "step": 1
        },
        {
          "name": "Количество мокрых точек",
          "type": "string",
          "min": 0,
          "step": 1
        },
        {
          "name": "Электрическая мощность",
          "type": "string",
          "min": 0,
          "step": 1
        },
        {
          "name": "Назначение",
          "type": "select",
          "options": ["1", "2"]
        },
        {
          "name": "Инфраструктура",
          "type": "string"
        },
        {
          "name": "Дополнительные услуги",
          "type": "string"
        },
        {
          "name": "Вход",
          "type": "string"
        },
        {
          "name": "Доступ",
          "type": "string"
        },
        {
          "name": "Ворота",
          "type": "switch"
        },
        {
          "name": "Крановое оборудование",
          "type": "switch"
        },
        {
          "name": "Вентиляция",
          "type": "switch"
        },
        {
          "name": "Кондиционирование",
          "type": "switch"
        },
        {
          "name": "Отопление",
          "type": "switch"
        },
        {
          "name": "Пожаротушение",
          "type": "switch"
        }
      ]
    },
    {
      "legend": "Мебель и оборудование",
      "name": "furniture",
      "fields": [
        {
          "name": "Оборудование",
          "type": "string"
        },
        {
          "name": "Состояние",
          "type": "string"
        },
        {
          "name": "Мебель",
          "type": "string"
        }
      ]
    },
    {
      "legend": "Парковка",
      "name": "parking",
      "fields": [
        {
          "name": "Парковка для офиса",
          "type": "switch"
        },
        {
          "name": "Парковка для склада",
          "type": "switch"
        },
        {
          "name": "Количество мест",
          "type": "string"
        },
        {
          "name": "Стоимость парковки",
          "type": "string"
        },
        {
          "name": "Тип парковки",
          "type": "string"
        },
        {
          "name": "Стоимость въезда",
          "type": "string"
        }
      ]
    },
    {
      "legend": "Постройка",
      "name": "building",
      "fields": [
        {
          "name": "Название здания",
          "type": "string"
        },
        {
          "name": "Год постройки",
          "type": "string"
        },
        {
          "name": "Тип здания",
          "type": "select",
          "options": ["1", "2"]
        },
        {
          "name": "Класс",
          "type": "string"
        },
        {
          "name": "Площадь здания",
          "type": "string"
        },
        {
          "name": "Линия",
          "type": "string"
        },
        {
          "name": "Девелопер",
          "type": "string"
        },
        {
          "name": "УК",
          "type": "string"
        }
      ]
    },
    {
      "legend": "Земля",
      "name": "land",
      "fields": [
        {
          "name": "Участок (площадь)",
          "type": "string"
        },
        {
          "name": "Участок (собственность/аренда)",
          "type": "string"
        },
        {
          "name": "Категория",
          "type": "string"
        }
      ]
    },
    {
      "legend": "Описание",
      "name": "description",
      "fields": []
    },
    {
      "legend": "Разное",
      "name": "other",
      "fields": []
    },
    {
      "legend": "Контакты",
      "name": "contacts",
      "fields": []
    }
  ]
}
